src/mul_te/mul_te.v
//
// Filename: "mul_te.v"
//
// Project: Троичный процессор для RISC-V
//
// Description: Операция инверсия трита. Мнемоника MUL_TE.
//
// Create date: 11.03.2025
// Edit date:   15.03.2025
//
//
// Author:      Vladimir Vasilev
// E-mail:      askfind@ya.ru
//
// GNU GENERAL PUBLIC LICENSE Version 3, 29 June 2007
//

// Таб.1 Алфавит троичной симметричной системы счисления
// +--------------------------+-------+-------+-------+
// | Числа                    |  -1   |   0   |   1   |
// +--------------------------+-------+-------+-------+
// | Логика                   | false |  nil  | true  |
// +--------------------------+-------+-------+-------+
// | Логика                   |   f   |   n   |   t   |
// +--------------------------+-------+-------+-------+
// | Символы                  |   -   |	  0   |	  +   |
// +--------------------------+-------+-------+-------+
// | Символы                  |   N   |	  Z   |	  P   |
// +--------------------------+-------+-------+-------+
// | Символы                  |   N   |	  O   |	  P   |
// +--------------------------+-------+-------+-------+
// | Символы                  |   0   |	  i   |	  1   |
// +--------------------------+-------+-------+-------+
// | Символы                  |   v   |	  0   |	  ^   |
// +--------------------------+-------+-------+-------+

//
// trit = {-1,0,1}  - значения трита
//
// Кодирование трита и интерпретация trit:
//
// a[1:0] -> {1,0} = '+1'
// a[1:0] -> {0,0} =  '0'
// a[1:0] -> {0,1} = '-1'
// a[1:0] -> {1,1} = 'Error'
//


// Таб.2 Троичное умножение
//       MUL
// .-----------------------.
// |     | -1  |  0  |  1  |
// |-----------------------|
// | -1  |  +  |  0  |  -  |
// |-----------------------|
// |  0  |  0  |  0  |  0  |
// |-----------------------|
// |  1  |  -  |  0  |  +  |
// .-----------------------.

module mul_te(a,b,c,err);

input  [1:0] a;
input  [1:0] b;
output reg[1:0] c;
output err;

always @(*) begin
    case ({a, b})
        4'b0101: c = 2'b10;
        4'b0100: c = 2'b00;
        4'b0110: c = 2'b01;
        4'b0001: c = 2'b00;
        4'b0000: c = 2'b00;
        4'b0010: c = 2'b00;
        4'b1001: c = 2'b01;
        4'b1000: c = 2'b00;
        4'b1010: c = 2'b10;
        default: c = 2'b00; // По умолчанию c=0
    endcase
end

assign err = ( (a == 2'b11) || (b == 2'b11) || (c == 2'b11) ) ? 1 : 0;

endmodule

src/mul_te/mul_te_testbench.v
//
// Filename: "mul_te_testbench.v"
//
// Project: Троичный процессор для RISC-V
//
// Create date: 11.03.2025
// Edit date:   15.03.2025
//
// Description: Тестирование операция инверсии трита. Мнемоника MUL_TE.
//
// Author:      Vladimir Vasilev
// E-mail:      askfind@ya.ru
//
// GNU GENERAL PUBLIC LICENSE Version 3, 29 June 2007
//

`timescale 1ps / 1ps

module mul_te_testbench;

    // Входной сигнал
    reg[1:0] a;
    reg[1:0] b;

    // Выходной сигнал
    wire[1:0] c;

    // Выходной сигнал
    wire err;

    // Instantiate the Unit Under Test (UUT)
    mul_te uut (
        .a(a),
        .b(b),
        .c(c),
        .err(err)
    );

    initial begin
        // Применение различных комбинаций входных сигналов
        #10 a = 2'b10;   // trit = +1
        #10 b = 2'b10;   // trit = +1
        #10 a = 2'b00;   // trit =  0
        #10 b = 2'b00;   // trit =  0
        #10 a = 2'b01;   // trit = -1
        #10 b = 2'b01;   // trit = -1
        #10 a = 2'b11;   // trit = error
        #10 b = 2'b11;   // trit = error

        // Завершение симуляции
        #10 $finish;
    end

    // Мониторинг сигналов
    initial begin
        $monitor("Time = %02t: trit a = %x, trit b = %x, trit c = %x, error = %b", $time, a, b, c, err);
    end

    initial begin
        $dumpfile ("extfile.vcd");
        $dumpvars (0, mul_te_testbench);
        #1;
     end

endmodule

src/mul_te/extfile.vcd
$date
	Sat Mar 15 20:06:51 2025
$end
$version
	Icarus Verilog
$end
$timescale
	1ps
$end
$scope module mul_te_testbench $end
$var wire 1 ! err $end
$var wire 2 " c [1:0] $end
$var reg 2 # a [1:0] $end
$var reg 2 $ b [1:0] $end
$scope module uut $end
$var wire 2 % a [1:0] $end
$var wire 2 & b [1:0] $end
$var wire 1 ! err $end
$var reg 2 ' c [1:0] $end
$upscope $end
$upscope $end
$enddefinitions $end
#0
$dumpvars
bx '
bx &
bx %
bx $
bx #
bx "
x!
$end
#10
b0 "
b0 '
b10 #
b10 %
#20
0!
b10 "
b10 '
b10 $
b10 &
#30
b0 "
b0 '
b0 #
b0 %
#40
b0 $
b0 &
#50
b1 #
b1 %
#60
b10 "
b10 '
b1 $
b1 &
#70
1!
b0 "
b0 '
b11 #
b11 %
#80
b11 $
b11 &
