src/add_full_te/add_full_te.v
//
// Filename: "add_full_te.v"
//
// Project: Троичный процессор для RISC-V
//
// Description: Операция инверсия трита. Мнемоника ADD_FULL_TE.
//
// Create date: 11.03.2025
// Edit date:   15.03.2025
//
//
// Author:      Vladimir Vasilev
// E-mail:      askfind@ya.ru
//
// GNU GENERAL PUBLIC LICENSE Version 3, 29 June 2007
//

// Таб.1 Алфавит троичной симметричной системы счисления
// +--------------------------+-------+-------+-------+
// | Числа                    |  -1   |   0   |   1   |
// +--------------------------+-------+-------+-------+
// | Логика                   | false |  nil  | true  |
// +--------------------------+-------+-------+-------+
// | Логика                   |   f   |   n   |   t   |
// +--------------------------+-------+-------+-------+
// | Символы                  |   -   |	  0   |	  +   |
// +--------------------------+-------+-------+-------+
// | Символы                  |   N   |	  Z   |	  P   |
// +--------------------------+-------+-------+-------+
// | Символы                  |   N   |	  O   |	  P   |
// +--------------------------+-------+-------+-------+
// | Символы                  |   0   |	  i   |	  1   |
// +--------------------------+-------+-------+-------+
// | Символы                  |   v   |	  0   |	  ^   |
// +--------------------------+-------+-------+-------+

//
// trit = {-1,0,1}  - значения трита
//
// Кодирование трита и интерпретация trit:
//
// a[1:0] -> {1,0} = '+1'
// a[1:0] -> {0,0} =  '0'
// a[1:0] -> {0,1} = '-1'
// a[1:0] -> {1,1} = 'Error'
//

// Таб.2 Таблица полного сумматора тритов
// .-----------------------------------------.
// | Перенос из n-1   -1  -1  -1   1   1   1 |
// | 1-е слагаемое    -1  -1  -1   1   1   1 |
// | 2-е слагаемое    -1   0   1  -1   0   1 |
// | Сумма   	       0   1  -1   1  -1   0 |
// | Перенос в n+1    -1  -1   0   0   1   1 |
// .-----------------------------------------.
// Полный сумматор двух тритов с переносом

module add_full_te (
    input  [1:0] carry_in,     // Перенос из n-1: -1, 0, 1
    input  [1:0] a,            // Первое слагаемое: -1, 0, 1
    input  [1:0] b,            // Второе слагаемое: -1, 0, 1
    output reg[1:0] sum,          // Сумма: -1, 0, 1
    output reg[1:0] carry_out,    // Перенос в n+1: -1, 0, 1
    output err                 // Достоверное вычисление
);

always @(*) begin
    case ({carry_in, a, b})
        // Перенос из n-1 = -1, Первое слагаемое = -1, Второе слагаемое = -1
        {2'b01, 2'b01, 2'b01}: begin
            sum = 2'b00;  // Сумма = 0
            carry_out = 2'b01; // Перенос в n+1 = -1
        end
        // Перенос из n-1 = -1, Первое слагаемое = -1, Второе слагаемое = 0
        {2'b01, 2'b01, 2'b00}: begin
            sum = 2'b10;  // Сумма = 1
            carry_out = 2'b01; // Перенос в n+1 = -1
        end
        // Перенос из n-1 = -1, Первое слагаемое = -1, Второе слагаемое = 1
        {2'b01, 2'b01, 2'b10}: begin
            sum = 2'b01;  // Сумма = -1
            carry_out = 2'b00; // Перенос в n+1 = 0
        end
        // Перенос из n-1 = 1, Первое слагаемое = 1, Второе слагаемое = -1
        {2'b10, 2'b10, 2'b01}: begin
            sum = 2'b10;  // Сумма = 1
            carry_out = 2'b00; // Перенос в n+1 = 0
        end
        // Перенос из n-1 = 1, Первое слагаемое = 1, Второе слагаемое = 0
        {2'b10, 2'b10, 2'b00}: begin
            sum = 2'b01;  // Сумма = -1
            carry_out = 2'b10; // Перенос в n+1 = 1
        end
        // Перенос из n-1 = 1, Первое слагаемое = 1, Второе слагаемое = 1
        {2'b10, 2'b10, 2'b10}: begin
            sum = 2'b00;  // Сумма = 0
            carry_out = 2'b10; // Перенос в n+1 = 1
        end
        // Остальные случаи (по умолчанию)
        default: begin
            sum = 2'b00;  // Сумма = 0
            carry_out = 2'b00; // Перенос в n+1 = 0
        end
    endcase
end

assign err = ( (carry_in == 2'b11) || (a == 2'b11) || (b == 2'b11) || (sum == 2'b11) || (carry_out == 2'b11) ) ? 1 : 0;

endmodule

src/add_full_te/add_full_te_testbench.v
//
// Filename: "add_full_te_testbench.v"
//
// Project: Троичный процессор для RISC-V
//
// Create date: 11.03.2025
// Edit date:   15.03.2025
//
// Description: Тестирование операция инверсии трита. Мнемоника ADD_FULL_TE.
//
// Author:      Vladimir Vasilev
// E-mail:      askfind@ya.ru
//
// GNU GENERAL PUBLIC LICENSE Version 3, 29 June 2007
//

`timescale 1ps / 1ps

module add_full_te_testbench;

    // Входной сигнал
    reg[1:0] carry_in;
    reg[1:0] a;
    reg[1:0] b;

    // Выходной сигнал
    wire [1:0] sum;
    wire [1:0] carry_out;
    wire err;

    // Instantiate the Unit Under Test (UUT)
    add_full_te uut (
        .carry_in(carry_in),
        .a(a),
        .b(b),
        .sum(sum),
        .carry_out(carry_out),
        .err(err)
    );

    initial begin
        // Применение различных комбинаций входных сигналов
        #10 carry_in = 2'b10;    // trit = +1
        #10 a = 2'b10;   // trit = +1
        #10 b = 2'b10;   // trit = +1
        #10 carry_in = 2'b10;    // trit = +1
        #10 a = 2'b00;   // trit =  0
        #10 b = 2'b00;   // trit =  0
        #10 carry_in = 2'b10;    // trit = +1
        #10 a = 2'b01;   // trit = -1
        #10 b = 2'b01;   // trit = -1
        #10 carry_in = 2'b10;    // trit = +1
        #10 a = 2'b11;   // trit = error
        #10 b = 2'b11;   // trit = error

        // Завершение симуляции
        #10 $finish;
    end

    // Мониторинг сигналов
    initial begin
        $monitor("Time = %02t: trit carry_in = %x, trit a = %x, trit b = %x, trit c = %x, error = %b", $time, carry_in, a, b, sum, carry_out, err);
    end

    initial begin
        $dumpfile ("extfile.vcd");
        $dumpvars (0, add_full_te_testbench);
        #1;
     end

endmodule

src/add_full_te/extfile.vcd
$date
	Sat Mar 15 20:49:32 2025
$end
$version
	Icarus Verilog
$end
$timescale
	1ps
$end
$scope module add_full_te_testbench $end
$var wire 2 ! sum [1:0] $end
$var wire 1 " err $end
$var wire 2 # carry_out [1:0] $end
$var reg 2 $ a [1:0] $end
$var reg 2 % b [1:0] $end
$var reg 2 & carry_in [1:0] $end
$scope module uut $end
$var wire 2 ' a [1:0] $end
$var wire 2 ( b [1:0] $end
$var wire 2 ) carry_in [1:0] $end
$var wire 1 " err $end
$var reg 2 * carry_out [1:0] $end
$var reg 2 + sum [1:0] $end
$upscope $end
$upscope $end
$enddefinitions $end
#0
$dumpvars
bx +
bx *
bx )
bx (
bx '
bx &
bx %
bx $
bx #
x"
bx !
$end
#10
b0 #
b0 *
b0 !
b0 +
b10 &
b10 )
#20
b10 $
b10 '
#30
0"
b10 #
b10 *
b10 %
b10 (
#50
b0 #
b0 *
b0 $
b0 '
#60
b0 %
b0 (
#80
b1 $
b1 '
#90
b1 %
b1 (
#110
1"
b11 $
b11 '
#120
b11 %
b11 (
